ntools/__init__.py
ntools/__main__.py
ntools/_modifying.py
ntools/cli.py
ntools-0.1.0.dist-info/entry_points.txt
ntools-0.1.0.dist-info/LICENSE
ntools-0.1.0.dist-info/WHEEL
ntools-0.1.0.dist-info/METADATA
ntools-0.1.0.dist-info/RECORD
