Metadata-Version: 2.1
Name: ntools
Version: 0.1.0
Summary: 
Author: metatooling
Author-email: metatooling@cordaz.com
Requires-Python: >=3.7,<4.0
Classifier: Programming Language :: Python :: 3
Classifier: Programming Language :: Python :: 3.7
Classifier: Programming Language :: Python :: 3.8
Provides-Extra: docs
Requires-Dist: attrs
Requires-Dist: click
